{
    "props": {
        "data": {
            "id": "__row_index__",
            "projection": {
                "x": "projection_v3_x",
                "y": "projection_v3_y"
            }
        },
        "embeddingViewLabels": [
            {
                "x": 0.3215374338640872,
                "y": -1.3446112414934202,
                "text": "Group 0",
                "level": 0,
                "priority": 10
            },
            {
                "x": 1.971919935619607,
                "y": 0.724436471706265,
                "text": "Group 1",
                "level": 0,
                "priority": 10
            },
            {
                "x": -3.243276721188861,
                "y": 0.7960389440436291,
                "text": "Group 2",
                "level": 0,
                "priority": 10
            },
            {
                "x": -1.2660624387557144,
                "y": 1.145671519409511,
                "text": "Group 3",
                "level": 0,
                "priority": 10
            },
            {
                "x": 0.8795125515530972,
                "y": 1.643871448705633,
                "text": "Group 4",
                "level": 0,
                "priority": 10
            },
            {
                "x": 2.34397916985774,
                "y": -1.04884885438248,
                "text": "Group 5",
                "level": 0,
                "priority": 10
            },
            {
                "x": -1.6570094610581947,
                "y": -1.403404951582419,
                "text": "Group 6",
                "level": 0,
                "priority": 10
            },
            {
                "x": 3.6461601970608153,
                "y": -0.10007913745674853,
                "text": "Group 7",
                "level": 0,
                "priority": 10
            },
            {
                "x": -3.045044182317207,
                "y": -0.1476674016901607,
                "text": "Group 8",
                "level": 0,
                "priority": 10
            },
            {
                "x": -0.043211029266720075,
                "y": -0.043029060127733325,
                "text": "Group 9",
                "level": 0,
                "priority": 10
            }
        ]
    },
    "isStatic": true,
    "database": {
        "type": "wasm",
        "load": true
    },
    "name_column": "title",
    "label_column": "title",
    "color_by": "Prominence",
    "column_mappings": {
        "title": "title",
        "abstract": "abstract",
        "Prominence": "Prominence",
        "author_count": "author_count",
        "author_tier": "author_tier",
        "url": "url",
        "ss_citation_count": "ss_citation_count",
        "ss_influential_citations": "ss_influential_citations",
        "ss_tldr": "ss_tldr",
        "CitationTier": "CitationTier",
        "recency": "recency",
        "paper_source": "paper_source"
    },
    "labels": {
        "show": true,
        "font_size": 13,
        "opacity": 0.95,
        "offset": [
            0,
            -18
        ],
        "background": true,
        "background_opacity": 0.7,
        "text_color": "#ffffff"
    }
}