{
    "props": {
        "data": {
            "id": "__row_index__",
            "projection": {
                "x": "projection_v3_x",
                "y": "projection_v3_y"
            }
        },
        "embeddingViewLabels": [
            {
                "x": 2.605204426880513,
                "y": 1.0618991510786873,
                "text": "Group 0",
                "level": 0,
                "priority": 10
            },
            {
                "x": 3.1773047791535722,
                "y": 0.03928272853572125,
                "text": "Group 1",
                "level": 0,
                "priority": 10
            },
            {
                "x": -0.6945579844295449,
                "y": -0.2847951401429343,
                "text": "Group 2",
                "level": 0,
                "priority": 10
            },
            {
                "x": 1.8313278699378732,
                "y": -1.0166848111998403,
                "text": "Group 3",
                "level": 0,
                "priority": 10
            },
            {
                "x": -1.4892612193869277,
                "y": -1.5182856831980314,
                "text": "Group 4",
                "level": 0,
                "priority": 10
            },
            {
                "x": -3.5250695168759094,
                "y": -0.23413354718496354,
                "text": "Group 5",
                "level": 0,
                "priority": 10
            },
            {
                "x": -2.194643032332832,
                "y": 0.9574424671204426,
                "text": "Group 6",
                "level": 0,
                "priority": 10
            },
            {
                "x": 0.22080750078917813,
                "y": 1.1373062688655464,
                "text": "Group 7",
                "level": 0,
                "priority": 10
            }
        ]
    },
    "isStatic": true,
    "database": {
        "type": "wasm",
        "load": true
    },
    "name_column": "title",
    "label_column": "title",
    "color_by": "Prominence",
    "column_mappings": {
        "title": "title",
        "abstract": "abstract",
        "Prominence": "Prominence",
        "author_count": "author_count",
        "author_tier": "author_tier",
        "url": "url",
        "ss_citation_count": "ss_citation_count",
        "ss_influential_citations": "ss_influential_citations",
        "ss_tldr": "ss_tldr",
        "CitationTier": "CitationTier",
        "recency": "recency",
        "paper_source": "paper_source"
    }
}